inception2corpus.py
i2c_lib/__init__.py
i2c_lib/constants.py
i2c_lib/corpus_statistics.py
i2c_lib/inception_connection.py
i2c_lib/io_utils.py
i2c_lib/preprocessing.py
i2c_lib/prompt_utils.py
i2c_lib/serialization.py
inception2corpus-0.1.2.dist-info/LICENSE
inception2corpus-0.1.2.dist-info/METADATA
inception2corpus-0.1.2.dist-info/WHEEL
inception2corpus-0.1.2.dist-info/entry_points.txt
inception2corpus-0.1.2.dist-info/top_level.txt
inception2corpus-0.1.2.dist-info/RECORD
