Metadata-Version: 2.1
Name: inception2corpus
Version: 0.1.2
Summary: A CLI for retrieving a corpus annotated with named entities from INCEpTION to an archived, reusable and versionable corpus.
Home-page: https://github.com/NER4Archives-project/inception2corpus-CLI
Author: Lucas Terriel
License: MIT
Classifier: License :: OSI Approved :: MIT License
Classifier: Intended Audience :: Developers
Classifier: Intended Audience :: Education
Classifier: Intended Audience :: Science/Research
Classifier: Programming Language :: Python :: 3.7
Classifier: Programming Language :: Python :: 3.8
Classifier: Operating System :: OS Independent
Requires-Python: >=3.7
License-File: LICENSE
Requires-Dist: dkpro-cassis (==0.7.2)
Requires-Dist: pycaprio (==0.2.0)
Requires-Dist: click (==8.1.3)
Requires-Dist: requests (==2.28.1)
Requires-Dist: xmi2conll (==0.1.6)
Requires-Dist: prompt-toolkit (==3.0.30)
Requires-Dist: nltk (==3.7)
Requires-Dist: PyYAML (==6.0)
Requires-Dist: termcolor (==2.0.1)
Requires-Dist: pyfiglet (==0.8.post1)
Requires-Dist: numpy (==1.22.0)
Requires-Dist: pandas (==1.3.5)
Requires-Dist: scikit-learn (==1.0.2)
Requires-Dist: tqdm (==4.64.1)
Requires-Dist: lxml (==4.9.1)
